Metadata-Version: 2.1
Name: manifest-ml
Version: 0.1.9
Summary: Manifest for Prompting Foundation Models.
Home-page: https://github.com/HazyResearch/manifest
Author: Laurel Orr
Author-email: laurel.orr@numbersstation.ai
License: Apache 2.0
Classifier: Programming Language :: Python
Classifier: Programming Language :: Python :: 3
Classifier: Programming Language :: Python :: 3.10
Classifier: Topic :: Scientific/Engineering :: Artificial Intelligence
Requires-Python: >=3.10.0
License-File: LICENSE
Requires-Dist: numpy >=1.20.0
Requires-Dist: pydantic <2.0,>=1.9.0
Requires-Dist: redis >=4.3.1
Requires-Dist: requests >=2.27.1
Requires-Dist: aiohttp >=3.8.0
Requires-Dist: sqlitedict >=2.0.0
Requires-Dist: tenacity >=8.2.0
Requires-Dist: tiktoken >=0.3.0
Requires-Dist: xxhash >=3.0.0
Provides-Extra: all
Requires-Dist: pytest-cov >=3.0.0 ; extra == 'all'
Requires-Dist: accelerate >=0.10.0 ; extra == 'all'
Requires-Dist: docformatter >=1.4 ; extra == 'all'
Requires-Dist: pytest >=7.0.0 ; extra == 'all'
Requires-Dist: sphinx-rtd-theme >=0.5.1 ; extra == 'all'
Requires-Dist: python-dotenv >=0.20.0 ; extra == 'all'
Requires-Dist: types-protobuf >=3.19.21 ; extra == 'all'
Requires-Dist: pre-commit >=2.14.0 ; extra == 'all'
Requires-Dist: diffusers >=0.6.0 ; extra == 'all'
Requires-Dist: sphinx-autobuild ; extra == 'all'
Requires-Dist: fastapi >=0.70.0 ; extra == 'all'
Requires-Dist: deepspeed >=0.10.0 ; extra == 'all'
Requires-Dist: types-requests >=2.27.29 ; extra == 'all'
Requires-Dist: types-redis >=4.2.6 ; extra == 'all'
Requires-Dist: types-xxhash >=3.0.0 ; extra == 'all'
Requires-Dist: flake8-docstrings >=1.6.0 ; extra == 'all'
Requires-Dist: transformers >=4.29.0 ; extra == 'all'
Requires-Dist: nbsphinx >=0.8.0 ; extra == 'all'
Requires-Dist: types-pillow >=9.0.0 ; extra == 'all'
Requires-Dist: pg8000 ; extra == 'all'
Requires-Dist: recommonmark >=0.7.1 ; extra == 'all'
Requires-Dist: autopep8 >=1.6.0 ; extra == 'all'
Requires-Dist: flake8 >=4.0.0 ; extra == 'all'
Requires-Dist: twine ; extra == 'all'
Requires-Dist: cloud-sql-python-connector[pg8000] >=1.0.0 ; extra == 'all'
Requires-Dist: pillow >=9.0.0 ; extra == 'all'
Requires-Dist: sentence-transformers >=2.2.0 ; extra == 'all'
Requires-Dist: torch >=1.8.0 ; extra == 'all'
Requires-Dist: types-python-dateutil >=2.8.16 ; extra == 'all'
Requires-Dist: tokenizers >=0.13.3 ; extra == 'all'
Requires-Dist: types-setuptools >=57.4.17 ; extra == 'all'
Requires-Dist: isort >=5.13.2 ; extra == 'all'
Requires-Dist: pep8-naming >=0.12.1 ; extra == 'all'
Requires-Dist: black >=22.3.0 ; extra == 'all'
Requires-Dist: mypy >=0.950 ; extra == 'all'
Requires-Dist: Flask >=2.1.2 ; extra == 'all'
Requires-Dist: types-PyYAML >=6.0.7 ; extra == 'all'
Requires-Dist: sqlalchemy ; extra == 'all'
Requires-Dist: uvicorn >=0.18.0 ; extra == 'all'
Provides-Extra: api
Requires-Dist: accelerate >=0.10.0 ; extra == 'api'
Requires-Dist: deepspeed >=0.10.0 ; extra == 'api'
Requires-Dist: diffusers >=0.6.0 ; extra == 'api'
Requires-Dist: Flask >=2.1.2 ; extra == 'api'
Requires-Dist: sentence-transformers >=2.2.0 ; extra == 'api'
Requires-Dist: torch >=1.8.0 ; extra == 'api'
Requires-Dist: transformers >=4.29.0 ; extra == 'api'
Requires-Dist: tokenizers >=0.13.3 ; extra == 'api'
Provides-Extra: app
Requires-Dist: fastapi >=0.70.0 ; extra == 'app'
Requires-Dist: uvicorn >=0.18.0 ; extra == 'app'
Provides-Extra: dev
Requires-Dist: autopep8 >=1.6.0 ; extra == 'dev'
Requires-Dist: black >=22.3.0 ; extra == 'dev'
Requires-Dist: isort >=5.13.2 ; extra == 'dev'
Requires-Dist: flake8 >=4.0.0 ; extra == 'dev'
Requires-Dist: flake8-docstrings >=1.6.0 ; extra == 'dev'
Requires-Dist: mypy >=0.950 ; extra == 'dev'
Requires-Dist: pep8-naming >=0.12.1 ; extra == 'dev'
Requires-Dist: docformatter >=1.4 ; extra == 'dev'
Requires-Dist: pytest >=7.0.0 ; extra == 'dev'
Requires-Dist: pytest-cov >=3.0.0 ; extra == 'dev'
Requires-Dist: python-dotenv >=0.20.0 ; extra == 'dev'
Requires-Dist: sphinx-rtd-theme >=0.5.1 ; extra == 'dev'
Requires-Dist: nbsphinx >=0.8.0 ; extra == 'dev'
Requires-Dist: recommonmark >=0.7.1 ; extra == 'dev'
Requires-Dist: pre-commit >=2.14.0 ; extra == 'dev'
Requires-Dist: types-redis >=4.2.6 ; extra == 'dev'
Requires-Dist: types-requests >=2.27.29 ; extra == 'dev'
Requires-Dist: types-PyYAML >=6.0.7 ; extra == 'dev'
Requires-Dist: types-protobuf >=3.19.21 ; extra == 'dev'
Requires-Dist: types-python-dateutil >=2.8.16 ; extra == 'dev'
Requires-Dist: types-setuptools >=57.4.17 ; extra == 'dev'
Requires-Dist: types-pillow >=9.0.0 ; extra == 'dev'
Requires-Dist: types-xxhash >=3.0.0 ; extra == 'dev'
Requires-Dist: sphinx-autobuild ; extra == 'dev'
Requires-Dist: twine ; extra == 'dev'
Provides-Extra: diffusers
Requires-Dist: pillow >=9.0.0 ; extra == 'diffusers'
Provides-Extra: gcp
Requires-Dist: pg8000 ; extra == 'gcp'
Requires-Dist: cloud-sql-python-connector[pg8000] >=1.0.0 ; extra == 'gcp'
Requires-Dist: sqlalchemy ; extra == 'gcp'
